{
  "version": 1,
  "slots": {
    "intro": {
      "file": "models/animations/boot.fbx",
      "loop": "once",
      "priority": 20,
      "layer": "gesture",
      "interrupt": true,
      "fadeIn": 0.2,
      "fadeOut": 0.2,
      "tags": ["startup"]
    },
    "idle": {
      "file": "models/animations/idle.fbx",
      "loop": "repeat",
      "priority": 0,
      "layer": "base",
      "interrupt": false,
      "fadeIn": 0.35,
      "fadeOut": 0.25,
      "tags": ["base"]
    },
    "headTap": {
      "file": "models/animations/head.fbx",
      "loop": "once",
      "priority": 10,
      "layer": "gesture",
      "interrupt": true,
      "fadeIn": 0.15,
      "fadeOut": 0.2,
      "tags": ["interaction", "head"]
    },
    "legTap": {
      "file": "models/animations/leg.fbx",
      "loop": "once",
      "priority": 10,
      "layer": "gesture",
      "interrupt": true,
      "fadeIn": 0.15,
      "fadeOut": 0.2,
      "tags": ["interaction", "lower_body"]
    },
    "armTap": {
      "file": "models/animations/arm_stretch.fbx",
      "loop": "once",
      "priority": 10,
      "layer": "gesture",
      "interrupt": true,
      "fadeIn": 0.15,
      "fadeOut": 0.2,
      "tags": ["interaction", "upper_body"]
    },
    "bodyTap": {
      "fallbackSlot": "headTap",
      "tags": ["interaction", "body"]
    },
    "chat": {
      "fallbackSlot": "armTap",
      "tags": ["interaction", "chat"]
    },
    "speaking": {
      "fallbackSlot": "idle",
      "loop": "repeat",
      "layer": "base",
      "tags": ["speech"]
    },
    "listening": {
      "fallbackSlot": "idle",
      "loop": "repeat",
      "layer": "base",
      "tags": ["listening"]
    }
  },
  "proceduralFallbacks": {
    "idle": true,
    "intro": true,
    "headTap": true,
    "legTap": true,
    "armTap": true,
    "bodyTap": true,
    "chat": true,
    "speaking": true,
    "listening": true
  }
}
